tcolr/__init__.py
tcolr/__main__.py
tcolr/tcolr.py
tcolr-0.2.0.dist-info/METADATA
tcolr-0.2.0.dist-info/WHEEL
tcolr-0.2.0.dist-info/entry_points.txt
tcolr-0.2.0.dist-info/top_level.txt
tcolr-0.2.0.dist-info/RECORD
