Metadata-Version: 2.1
Name: tcolr
Version: 0.2.0
Summary: A simple terminal colorizer
Requires-Python: >=3.8
Requires-Dist: rich >13.8.0
Requires-Dist: pyyaml >5.4.1
Requires-Dist: asteval >1.0.5
